hunabku_siiu/__init__.py
hunabku_siiu/_version.py
hunabku_siiu/endpoints/SIIU.py
Hunabku_siiu-0.0.6.dist-info/METADATA
Hunabku_siiu-0.0.6.dist-info/WHEEL
Hunabku_siiu-0.0.6.dist-info/top_level.txt
Hunabku_siiu-0.0.6.dist-info/RECORD
